otmt/__init__.py
otmt/archive_information.py
otmt/argument_processing.py
otmt/collection_measures.py
otmt/collectionmodel.py
otmt/input_types.py
otmt/measuremodel.py
otmt/metadata_calcluations.py
otmt/output_types.py
otmt/timemap.py
otmt/timemap_measures.py
otmt/version.py
otmt-1.0.5.data/scripts/cluster_by_simhash
otmt-1.0.5.data/scripts/detect_off_topic
otmt-1.0.5.data/scripts/exclude_duplicates
otmt-1.0.5.data/scripts/select_by_language
otmt-1.0.5.data/scripts/select_high_quality
otmt-1.0.5.data/scripts/slice_by_datetime
otmt-1.0.5.dist-info/LICENSE.txt
otmt-1.0.5.dist-info/METADATA
otmt-1.0.5.dist-info/WHEEL
otmt-1.0.5.dist-info/top_level.txt
otmt-1.0.5.dist-info/zip-safe
otmt-1.0.5.dist-info/RECORD
