Metadata-Version: 2.1
Name: otmt
Version: 1.0.5
Summary: Tools for determining if web archive collecions are Off-Topic
Home-page: https://github.com/oduwsdl/off-topic-memento-toolkit
Author: Shawn M. Jones
Author-email: jones.shawn.m@gmail.com
License: MIT
Keywords: webarchives memento similarity offtopic
Platform: UNKNOWN
Classifier: Development Status :: 3 - Alpha
Classifier: Intended Audience :: Developers
Classifier: Intended Audience :: Information Technology
Classifier: Intended Audience :: Science/Research
Classifier: Topic :: Internet :: WWW/HTTP
Classifier: Topic :: Text Processing
Classifier: Topic :: Scientific/Engineering
Classifier: Topic :: Software Development :: Libraries :: Python Modules
Classifier: Topic :: Utilities
Classifier: License :: OSI Approved :: MIT License
Classifier: Programming Language :: Python :: 3.6
License-File: LICENSE.txt
Requires-Dist: aiu
Requires-Dist: bs4
Requires-Dist: distance
Requires-Dist: gensim
Requires-Dist: html5lib
Requires-Dist: justext
Requires-Dist: langdetect
Requires-Dist: lxml
Requires-Dist: nltk
Requires-Dist: numpy
Requires-Dist: paramiko
Requires-Dist: requests
Requires-Dist: requests-cache
Requires-Dist: requests-futures
Requires-Dist: scikit-learn
Requires-Dist: scipy
Requires-Dist: simhash
Requires-Dist: warcio
